setup.py
je/__init__.py
je/cache.py
je/commands.py
je/completion.py
je/configuration.py
je/jenkins.py
je/main.py
je/work.py
je.egg-info/PKG-INFO
je.egg-info/SOURCES.txt
je.egg-info/dependency_links.txt
je.egg-info/entry_points.txt
je.egg-info/not-zip-safe
je.egg-info/requires.txt
je.egg-info/top_level.txt