Metadata-Version: 1.0
Name: je
Version: 0.13
Summary: jenkins system tests CLI
Home-page: UNKNOWN
Author: GigaSpaces
Author-email: cosmo-admin@gigaspaces.com
License: Apache License, Version 2.0
Platform: UNKNOWN
